cfa_zeus-4.0.1.data/data/sample/zeus/file_date_sample1.py
cfa_zeus-4.0.1.data/data/sample/zeus/file_path_sample1.py
cfa_zeus-4.0.1.data/data/sample/zeus/log_sample1.py
cfa_zeus-4.0.1.data/data/sample/zeus/log_sample2.py
cfa_zeus-4.0.1.data/data/sample/zeus/log_sample3.py
cfa_zeus-4.0.1.data/data/sample/zeus/log_sample4.py
cfa_zeus-4.0.1.data/data/sample/zeus/parser_ini_sample1.ini
cfa_zeus-4.0.1.data/data/sample/zeus/parser_ini_sample1.py
cfa_zeus-4.0.1.data/data/sample/zeus/parser_xml_sample1.py
cfa_zeus-4.0.1.data/data/sample/zeus/parser_xml_sample1.xml
cfa_zeus-4.0.1.data/data/sample/zeus/run.ini
cfa_zeus-4.0.1.data/scripts/zcrypt.py
cfa_zeus-4.0.1.data/scripts/zkey.py
cfa_zeus-4.0.1.dist-info/DESCRIPTION.rst
cfa_zeus-4.0.1.dist-info/METADATA
cfa_zeus-4.0.1.dist-info/RECORD
cfa_zeus-4.0.1.dist-info/WHEEL
cfa_zeus-4.0.1.dist-info/metadata.json
cfa_zeus-4.0.1.dist-info/top_level.txt
zeus/__init__.py
zeus/_version.py
zeus/crypto.py
zeus/date.py
zeus/exception.py
zeus/file.py
zeus/log.py
zeus/parser.py
