Metadata-Version: 2.0
Name: cfa-zeus
Version: 4.0.1
Summary: general tools: cryptography, file, parsing, log
Home-page: https://github.com/cfauchard/zeus
Author: Christophe Fauchard
Author-email: christophe.fauchard@gmail.com
License: GPLV3
Platform: UNKNOWN
